clubbi_utils/__init__.py
clubbi_utils/async_callable.py
clubbi_utils/data.py
clubbi_utils/json.py
clubbi_utils/json_logging.py
clubbi_utils/logger.py
clubbi_utils/logging.py
clubbi_utils/mailer.py
clubbi_utils/publisher.py
clubbi_utils/py.typed
clubbi_utils/slack_messenger.py
clubbi_utils/aws/__init__.py
clubbi_utils/aws/aws_http_event.py
clubbi_utils/aws/aws_s3_event.py
clubbi_utils/aws/aws_sqs_event.py
clubbi_utils/aws/decorator.py
clubbi_utils/aws/get_ssm_secret.py
clubbi_utils/aws/lambda_invoker.py
clubbi_utils/aws/s3_object_storage.py
clubbi_utils/aws/ses_mailer.py
clubbi_utils/aws/sns_publisher.py
clubbi_utils/aws/lambda/__init__.py
clubbi_utils/aws/lambda/http_events.py
clubbi_utils/aws/local_mocks/__init__.py
clubbi_utils/aws/local_mocks/s3_object_storage_local_mock.py
clubbi_utils/cli/__init__.py
clubbi_utils/cli/clubbi_sls_util/__init__.py
clubbi_utils/cli/clubbi_sls_util/utils.py
clubbi_utils/cli/clubbi_sls_util/cmds/__init__.py
clubbi_utils/cli/clubbi_sls_util/cmds/deploy_lambda_layer.py
clubbi_utils/common/__init__.py
clubbi_utils/common/async_lambda.py
clubbi_utils/common/async_messenger.py
clubbi_utils/common/batched_gather.py
clubbi_utils/common/clubbi_validation_error.py
clubbi_utils/common/iter_as_chunks.py
clubbi_utils/common/parse_obj_list_with_errors.py
clubbi_utils/common/pydantic_types.py
clubbi_utils/common/timeit.py
clubbi_utils/common/undefined.py
clubbi_utils/common/csv_utils/__init__.py
clubbi_utils/common/csv_utils/base_model_collection_to_csv.py
clubbi_utils/common/typing/__init__.py
clubbi_utils/common/typing/lambda_context.py
clubbi_utils/mysql/__init__.py
clubbi_utils/mysql/decorator.py
clubbi_utils/mysql/mysql_connector.py
clubbi_utils/mysql/print_literal_query.py
clubbi_utils/mysql/retry_query_on_deadlock.py
clubbi_utils/operators/__init__.py
clubbi_utils/operators/none_assertion.py
clubbi_utils/operators/none_coalesce.py
clubbi_utils/postgres/__init__.py
clubbi_utils/postgres/advisory_locker.py
clubbi_utils-6.2.1.dist-info/LICENSE
clubbi_utils-6.2.1.dist-info/METADATA
clubbi_utils-6.2.1.dist-info/WHEEL
clubbi_utils-6.2.1.dist-info/entry_points.txt
clubbi_utils-6.2.1.dist-info/top_level.txt
clubbi_utils-6.2.1.dist-info/RECORD
